bootlick/__init__.py
bootlick/config.py
bootlick/nse_company_info.py
bootlick/nse_eod_prices.py
bootlick/screener.py
bootlick/screener_metrics.py
bootlick/testing.py
bootlick/config/config_sample.yaml
bootlick-0.1.4.dist-info/METADATA
bootlick-0.1.4.dist-info/WHEEL
bootlick-0.1.4.dist-info/top_level.txt
bootlick-0.1.4.dist-info/RECORD
