Metadata-Version: 2.4
Name: bootlick
Version: 0.1.4
Summary: A package for specific websites
Author-email: Unknown <unknown@example.com>
License-Expression: MIT
Requires-Dist: chameli
Requires-Dist: ohlcutils
Requires-Dist: nse[server]
